{
  "project_info": {
    "project_number": "562620006318",
    "project_id": "redpay-c9810",
    "storage_bucket": "redpay-c9810.firebasestorage.app"
  },
  "client": [
    {
      "client_info": {
        "mobilesdk_app_id": "1:562620006318:android:ab26c103d10c35f821d23f",
        "android_client_info": {
          "package_name": "com.emircivelek.redpay"
        }
      },
      "oauth_client": [],
      "api_key": [
        {
          "current_key": "AIzaSyAdOsGQlcHnzogvJWtp5J5v0pC_Ro65RR8"
        }
      ],
      "services": {
        "appinvite_service": {
          "other_platform_oauth_client": []
        }
      }
    }
  ],
  "configuration_version": "1"
}